<annotation>
	<folder>images</folder>
	<filename>h (79).jpg</filename>
	<path>C:\Users\Feroz\Desktop\FYP_stealingDeteciton-master\data\images\h (79).jpg</path>
	<source>
		<database>Unknown</database>
	</source>
	<size>
		<width>2448</width>
		<height>3264</height>
		<depth>3</depth>
	</size>
	<segmented>0</segmented>
	<object>
		<name>implantableport</name>
		<pose>Unspecified</pose>
		<truncated>0</truncated>
		<difficult>0</difficult>
		<bndbox>
			<xmin>554</xmin>
			<ymin>955</ymin>
			<xmax>1711</xmax>
			<ymax>2307</ymax>
		</bndbox>
	</object>
</annotation>
