<annotation>
	<folder>images</folder>
	<filename>j (408).jpg</filename>
	<path>C:\Users\Feroz\Desktop\FYP_stealingDeteciton-master\data\images\j (408).jpg</path>
	<source>
		<database>Unknown</database>
	</source>
	<size>
		<width>3264</width>
		<height>2448</height>
		<depth>3</depth>
	</size>
	<segmented>0</segmented>
	<object>
		<name>nokor_non_coring_needle</name>
		<pose>Unspecified</pose>
		<truncated>0</truncated>
		<difficult>0</difficult>
		<bndbox>
			<xmin>950</xmin>
			<ymin>874</ymin>
			<xmax>2865</xmax>
			<ymax>1377</ymax>
		</bndbox>
	</object>
</annotation>
